CHANGES
LICENSE
MANIFEST.in
README
setup.cfg
setup.py
docs/Makefile
docs/make.bat
docs/source/api.rst
docs/source/conf.py
docs/source/index.rst
yaak/__init__.py
yaak/inject.py
yaak.inject.egg-info/PKG-INFO
yaak.inject.egg-info/SOURCES.txt
yaak.inject.egg-info/dependency_links.txt
yaak.inject.egg-info/namespace_packages.txt
yaak.inject.egg-info/requires.txt
yaak.inject.egg-info/top_level.txt
yaak/tests/__init__.py
yaak/tests/test_inject.py