Metadata-Version: 1.0
Name: yaak.inject
Version: 0.2.1
Summary: A dependency injection framework for your python applications
Home-page: http://bitbucket.org/sprat/yaak.inject
Author: Sylvain Prat
Author-email: sylvain.prat+yaak.inject@gmail.com
License: MIT License
Download-URL: http://pypi.python.org/pypi/yaak.inject
Keywords: dependency,injection,inject
Platform: any
Classifier: Development Status :: 4 - Beta
Classifier: Environment :: Console
Classifier: Environment :: Web Environment
Classifier: Environment :: Win32 (MS Windows)
Classifier: Environment :: X11 Applications
Classifier: Environment :: MacOS X
Classifier: Environment :: Other Environment
Classifier: Intended Audience :: Developers
Classifier: License :: OSI Approved :: MIT License
Classifier: Operating System :: OS Independent
Classifier: Programming Language :: Python :: 2.6
Classifier: Programming Language :: Python :: 2.7
Classifier: Topic :: Software Development :: Libraries :: Application Frameworks
